MANIFEST.in
README
requirements.txt
setup.py
PgStructure.egg-info/PKG-INFO
PgStructure.egg-info/SOURCES.txt
PgStructure.egg-info/dependency_links.txt
PgStructure.egg-info/entry_points.txt
PgStructure.egg-info/not-zip-safe
PgStructure.egg-info/requires.txt
PgStructure.egg-info/top_level.txt
pgstructure/__init__.py
pgstructure/pgstructure.py
pgstructure/templates/base.html
pgstructure/templates/column_list.html
pgstructure/templates/foreign_key_link.html
pgstructure/templates/schema_list.html
pgstructure/templates/table_list.html