Metadata-Version: 1.1
Name: PgStructure
Version: 0.0.1
Summary: You can check the database structure of PostgreSQL
Home-page: http://github.com/narusemotoki/pgstructure
Author: Motoki Naruse
Author-email: motoki@naru.se
License: GPLv3
Keywords: postgresql
Platform: UNKNOWN
Classifier: Topic :: Database
Classifier: Environment :: Web Environment
Classifier: Framework :: Bottle
Classifier: Development Status :: 1 - Planning
Classifier: Intended Audience :: Developers
Classifier: License :: OSI Approved :: GNU General Public License v3 (GPLv3)
Classifier: Natural Language :: English
Classifier: Operating System :: POSIX
Classifier: Programming Language :: Python :: 2.7
